lelekov_remote_lab/__init__.py
lelekov_remote_lab/communicator.py
lelekov_remote_lab/plotter.py
lelekov_remote_lab-0.0.3.dist-info/METADATA
lelekov_remote_lab-0.0.3.dist-info/WHEEL
lelekov_remote_lab-0.0.3.dist-info/top_level.txt
lelekov_remote_lab-0.0.3.dist-info/RECORD
