Metadata-Version: 2.1
Name: lelekov-remote-lab
Version: 0.0.3
Summary: Библиотека для управления системой ориентации
License: UNKNOWN
Platform: UNKNOWN
Requires-Dist: matplotlib
Requires-Dist: numpy
